celldancer/__init__.py
celldancer/cdplt.py
celldancer/compute_cell_velocity.py
celldancer/diffusion.py
celldancer/embedding_kinetic_para.py
celldancer/pseudo_time.py
celldancer/sampling.py
celldancer/simulation.py
celldancer/utilities.py
celldancer/velocity_estimation.py
celldancer/model/branch.pt
celldancer/model/circle.pt
celldancer/plotting/__init__.py
celldancer/plotting/cell.py
celldancer/plotting/colormap.py
celldancer/plotting/gene.py
celldancer/plotting/graph.py
celldancer-1.1.7.dist-info/LICENSE
celldancer-1.1.7.dist-info/METADATA
celldancer-1.1.7.dist-info/WHEEL
celldancer-1.1.7.dist-info/top_level.txt
celldancer-1.1.7.dist-info/RECORD
