Metadata-Version: 2.1
Name: celldancer
Version: 1.1.7
Summary: Study RNA velocity through neural network.
Author: Wang Lab
Author-email: gwang2@houstonmethodist.org
Project-URL: cellDancer, https://github.com/GuangyuWangLab2021/cellDancer
Project-URL: Documentation, https://guangyuwanglab2021.github.io/cellDancer_website/
Classifier: Programming Language :: Python :: 3
Classifier: License :: OSI Approved :: MIT License
Classifier: Operating System :: OS Independent
Requires-Python: >=3.7.6
License-File: LICENSE
Requires-Dist: pytorch-lightning (==1.5.2)
Requires-Dist: torch (==1.10.0)
Requires-Dist: pandas (==1.3.4)
Requires-Dist: numpy (==1.20.3)
Requires-Dist: anndata (==0.8.0)
Requires-Dist: tqdm (==4.62.3)
Requires-Dist: scikit-learn (==1.0.1)
Requires-Dist: scipy (==1.7.2)
Requires-Dist: joblib (==1.1.0)
Requires-Dist: scikit-image (==0.19.2)
Requires-Dist: statsmodels (==0.13.1)
Requires-Dist: matplotlib (==3.5.3)
Requires-Dist: seaborn (==0.11.2)
Requires-Dist: datashader (==0.14.0)
Requires-Dist: bezier (==2021.2.12)
Requires-Dist: umap-learn (==0.5.2)
Requires-Dist: jupyterlab
Requires-Dist: setuptools (==59.5.0)
Requires-Dist: setuptools-scm (==6.3.2)
